codewars/__init__.py
codewars/bluetooth/__init__.py
codewars/logger/__init__.py
codewars/scraper/__init__.py
codewars/surf/__init__.py
codewars/unittest/__init__.py
codewars/unittest/testScraper.py
codewars/unittest/testSurf.py
codewars/wifi/__init__.py
codewars-0.0.63.dist-info/LICENSE
codewars-0.0.63.dist-info/METADATA
codewars-0.0.63.dist-info/WHEEL
codewars-0.0.63.dist-info/top_level.txt
codewars-0.0.63.dist-info/RECORD
