Metadata-Version: 2.1
Name: codewars
Version: 0.0.63
Summary: A toolbox for daily use. This is just a toolbox to make my life easier. Maybe yours too..
Home-page: UNKNOWN
Author: 0x78f1935
Author-email: 
License: UNKNOWN
Platform: UNKNOWN
Classifier: Programming Language :: Python :: 3.6
Classifier: License :: OSI Approved :: Mozilla Public License 2.0 (MPL 2.0)
Classifier: Operating System :: POSIX :: Linux
Classifier: Development Status :: 1 - Planning
Requires-Python: >=3.6.*
Requires-Dist: aiohttp
Requires-Dist: beautifulsoup4
Requires-Dist: ipython
Requires-Dist: lxml
Requires-Dist: PyBluez
Requires-Dist: scapy
